django_app_permissions_access_request/__init__.py
django_app_permissions_access_request/admin.py
django_app_permissions_access_request/apps.py
django_app_permissions_access_request/models.py
django_app_permissions_access_request/tests.py
django_app_permissions_access_request/urls.py
django_app_permissions_access_request/views.py
django_app_permissions_access_request/migrations/0001_initial.py
django_app_permissions_access_request/migrations/0002_request_description.py
django_app_permissions_access_request/migrations/__init__.py
django_app_permissions_access_request/templates/app_permissions_access_approval.html
django_app_permissions_access_request/templates/app_permissions_access_approval_list.html
django_app_permissions_access_request/templates/app_permissions_access_base.html
django_app_permissions_access_request/templates/app_permissions_access_request.html
django_app_permissions_access_request/templates/app_permissions_access_request_list.html
django_app_permissions_access_request/templates/approval.html
django_app_permissions_access_request/templates/approval_list.html
django_app_permissions_access_request/templates/base.html
django_app_permissions_access_request/templates/request.html
django_app_permissions_access_request/templates/request_list.html
django_app_permissions_access_request-0.0.5.dist-info/LICENSE
django_app_permissions_access_request-0.0.5.dist-info/METADATA
django_app_permissions_access_request-0.0.5.dist-info/WHEEL
django_app_permissions_access_request-0.0.5.dist-info/top_level.txt
django_app_permissions_access_request-0.0.5.dist-info/RECORD
